TastyTopping-1.2.5.dist-info/WHEEL
TastyTopping-1.2.5.dist-info/DESCRIPTION.rst
TastyTopping-1.2.5.dist-info/RECORD
TastyTopping-1.2.5.dist-info/top_level.txt
TastyTopping-1.2.5.dist-info/METADATA
TastyTopping-1.2.5.dist-info/metadata.json
tastytopping/resource.py
tastytopping/auth.py
tastytopping/schema.py
tastytopping/meta.py
tastytopping/field.py
tastytopping/queryset.py
tastytopping/tastytypes.py
tastytopping/cache.py
tastytopping/factory.py
tastytopping/__init__.py
tastytopping/exceptions.py
tastytopping/lock.py
tastytopping/nested.py
tastytopping/api.py
