Metadata-Version: 2.0
Name: TastyTopping
Version: 1.2.5
Summary: An ORM for tastypie's API on the client-side.
Home-page: https://github.com/cboelsen/tastytopping
Author: Christian Boelsen
Author-email: christian.boelsen@hds.com
License: LGPLv3
Keywords: tastypie,client,django,rest,api,resource,orm
Platform: UNKNOWN
Classifier: Development Status :: 5 - Production/Stable
Classifier: Environment :: Console
Classifier: Environment :: Web Environment
Classifier: Framework :: Django
Classifier: Intended Audience :: Developers
Classifier: Intended Audience :: System Administrators
Classifier: License :: OSI Approved :: GNU Lesser General Public License v3 (LGPLv3)
Classifier: Operating System :: OS Independent
Classifier: Programming Language :: Python :: 2
Classifier: Programming Language :: Python :: 2.7
Classifier: Programming Language :: Python :: 3
Classifier: Programming Language :: Python :: 3.3
Classifier: Programming Language :: Python :: 3.4
Classifier: Topic :: Internet :: WWW/HTTP
Classifier: Topic :: Software Development :: Libraries :: Python Modules
Requires-Dist: requests (>=1.2.3)
